deprecat/__init__.py
deprecat/classic.py
deprecat/example.py
deprecat/sphinx.py
deprecat-2.1.3.dist-info/LICENSE.rst
deprecat-2.1.3.dist-info/METADATA
deprecat-2.1.3.dist-info/WHEEL
deprecat-2.1.3.dist-info/top_level.txt
deprecat-2.1.3.dist-info/RECORD
